{
    "city": "United Arab Emirates",
    "position": "Founder at MYRA INVESTMENTS | IMAGINE LEADER",
    "experience": [
        {
            "title": "Leader",
            "description_html": null,
            "duration": "Sep 2022 - Present 2 years 4 months",
            "start_date": "Sep 2022",
            "end_date": "Present",
            "duration_short": "2 years 4 months",
            "company": "IMAGINE",
            "company_id": "imagineone",
            "url": "",
            "company_logo_url": ""
        },
        {
            "title": "Founder",
            "location": "United Arab Emirates",
            "description": "Investment Firm focused on managing and investing Renewable Energy and Infrastructure Projects in Emerging Markets",
            "description_html": "Investment Firm focused on managing and investing Renewable Energy and Infrastructure Projects in Emerging Markets <!---->",
            "duration": "May 2018 - Present 6 years 8 months",
            "start_date": "May 2018",
            "end_date": "Present",
            "duration_short": "6 years 8 months",
            "company": "MYRA INVESTMENTS",
            "company_id": "myra-investments",
            "url": "",
            "company_logo_url": ""
        },
        {
            "title": "Investment Professional",
            "location": "Dubai, U.A.E.",
            "description": "Private Equity",
            "description_html": "Private Equity <!---->",
            "duration": "Dec 2015 Mar 2018 2 years 4 months",
            "start_date": "Dec 2015",
            "end_date": "Mar 2018",
            "duration_short": "2 years 4 months",
            "company": "The Abraaj Group",
            "company_id": "the-abraaj-group",
            "url": "",
            "company_logo_url": ""
        },
        {
            "title": "Vice President",
            "location": "Sydney, Australia",
            "description_html": null,
            "duration": "Feb 2015 Nov 2015 10 months",
            "start_date": "Feb 2015",
            "end_date": "Nov 2015",
            "duration_short": "10 months",
            "company": "Luminis Partners in affiliation with Evercore",
            "company_id": "luminis-partners",
            "url": "",
            "company_logo_url": ""
        },
        {
            "title": "Associate, Energy and Resources",
            "location": "Sydney, Australia",
            "description_html": null,
            "duration": "Nov 2012 Feb 2015 2 years 4 months",
            "start_date": "Nov 2012",
            "end_date": "Feb 2015",
            "duration_short": "2 years 4 months",
            "company": "CIMB",
            "company_id": "cimbmalaysia",
            "url": "",
            "company_logo_url": ""
        },
        {
            "title": "Associate - Energy and Resources",
            "location": "Sydney Area, Australia",
            "description_html": null,
            "duration": "Apr 2010 Nov 2012 2 years 8 months",
            "start_date": "Apr 2010",
            "end_date": "Nov 2012",
            "duration_short": "2 years 8 months",
            "company": "Royal Bank of Scotland",
            "company_id": "royal-bank-of-scotland",
            "url": "",
            "company_logo_url": ""
        },
        {
            "title": "Analyst - Corporate Finance",
            "location": "Sydney, Australia",
            "description_html": null,
            "duration": "Jul 2008 Mar 2010 1 year 9 months",
            "start_date": "Jul 2008",
            "end_date": "Mar 2010",
            "duration_short": "1 year 9 months",
            "company": "Deloitte",
            "company_id": "deloitte",
            "url": "",
            "company_logo_url": ""
        },
        {
            "title": "Engineering Thesis",
            "location": "Sydney, Australia",
            "description_html": null,
            "duration": "Feb 2008 Jul 2008 6 months",
            "start_date": "Feb 2008",
            "end_date": "Jul 2008",
            "duration_short": "6 months",
            "company": "Rio Tinto",
            "company_id": "rio-tinto",
            "url": "",
            "company_logo_url": ""
        },
        {
            "title": "Analyst",
            "location": "Sydney, Australia",
            "description_html": null,
            "duration": "Dec 2007 Feb 2008 3 months",
            "start_date": "Dec 2007",
            "end_date": "Feb 2008",
            "duration_short": "3 months",
            "company": "Citi",
            "company_id": "citi",
            "url": "",
            "company_logo_url": ""
        }
    ],
    "education": [
        {
            "title": "INSEAD",
            "degree": "Master of Business Administration (MBA)",
            "field": "MBA",
            "url": "",
            "start_year": "2013",
            "end_year": "2014",
            "description": "Activities and Societies: Treasurer - Student Council President - Energy Club President - Investment Banking Club",
            "description_html": "Activities and Societies: Treasurer - Student Council President - Energy Club President - Investment Banking Club",
            "institute_logo_url": ""
        },
        {
            "title": "Columbia Business School",
            "degree": "Executive Education - Certification",
            "field": "Value Investing",
            "url": "",
            "start_year": "2018",
            "end_year": "2018",
            "description": null,
            "description_html": null,
            "institute_logo_url": ""
        },
        {
            "title": "Kaplan Australia",
            "degree": "Dip. in Applied Finance",
            "url": "",
            "start_year": "2010",
            "end_year": "2012",
            "description": null,
            "description_html": null,
            "institute_logo_url": ""
        },
        {
            "title": "Institute of Chartered Accountants in Australia",
            "degree": "Master's Degree",
            "field": "Accounting",
            "url": "",
            "description": null,
            "description_html": null,
            "institute_logo_url": ""
        },
        {
            "title": "University of Technology, Sydney",
            "degree": "Bachelor's Degree",
            "field": "Bachelors of Engineering (First Class Hons.) / Bachelors of Business (with Distinction)",
            "url": "",
            "start_year": "2003",
            "end_year": "2008",
            "description": "Recipient of the the Manufacturing Engineering Prize Gold Medalist Dean's List 5 years",
            "description_html": "Recipient of the the Manufacturing Engineering Prize Gold MedalistDean's List 5 years <!---->",
            "institute_logo_url": ""
        }
    ],
    "courses": null,
    "certifications": [
        {
            "subtitle": "CA Institute Australia",
            "title": "chartered accountant"
        }
    ],
    "current_company_name": "IMAGINE",
    "publications": null,
    "patents": null,
    "projects": null,
    "honors_and_awards": null
}