{
    "id": "nikhita17",
    "name": "Nikhita Jain",
    "city": "New Delhi, Delhi, India",
    "country_code": "IN",
    "position": null,
    "about": "HR leader with 12 years of experience. Adept at Business Partnering, Talent Design\u00e2\u20ac\u00a6",
    "posts": null,
    "groups": null,
    "current_company": {
        "link": "",
        "name": "Airbnb",
        "company_id": "airbnb"
    },
    "experience": null,
    "people_also_viewed": [
        {
            "profile_link": "",
            "name": "Raghavendra Abhishek Rao",
            "about": null,
            "location": "New Delhi"
        },
        {
            "profile_link": "",
            "name": "Shruthi Nannikere",
            "about": null,
            "location": "Tallinn"
        },
        {
            "profile_link": "",
            "name": "Debasish Panda",
            "about": null,
            "location": "Hyderabad"
        },
        {
            "profile_link": "",
            "name": "Keerat Kaur",
            "about": null,
            "location": "Delhi, India"
        },
        {
            "profile_link": "",
            "name": "Sonam Singh",
            "about": null,
            "location": "Hyderabad"
        },
        {
            "profile_link": "",
            "name": "Riyas C S",
            "about": null,
            "location": "Bengaluru"
        },
        {
            "profile_link": "",
            "name": "Vinay S.",
            "about": null,
            "location": "Bengaluru"
        },
        {
            "profile_link": "",
            "name": "Yoshi S.",
            "about": "Amazonian : A talent acquisition enthusiast, a creative soul and may be your future colleague at Amazon!!",
            "location": "Bengaluru"
        },
        {
            "profile_link": "",
            "name": "Gunjan Sharma",
            "about": "HR Business Partner at LinkedIn",
            "location": "Bengaluru"
        },
        {
            "profile_link": "",
            "name": "Saumya Nigam",
            "about": null,
            "location": "Bengaluru"
        },
        {
            "profile_link": "",
            "name": "Kamran Rizvi",
            "about": null,
            "location": "Delhi, India"
        },
        {
            "profile_link": "",
            "name": "Abhinav Saurabh",
            "about": "Talent Acquisition Professional | Build the teams that shape Google\u00e2\u20ac\u2122s future",
            "location": "Bengaluru"
        },
        {
            "profile_link": "",
            "name": "Apoorv Kalia",
            "about": null,
            "location": "Gurugram"
        },
        {
            "profile_link": "",
            "name": "Divyanshi Tripathi",
            "about": "Technology Talent Discovery- EMEA | MBA in HR",
            "location": "United Kingdom"
        },
        {
            "profile_link": "",
            "name": "Gnanavel B",
            "about": null,
            "location": "Bengaluru"
        },
        {
            "profile_link": "",
            "name": "Shivangi Chauhan",
            "about": null,
            "location": "Bengaluru"
        },
        {
            "profile_link": "",
            "name": "Divya Agarwal ( She/Her)",
            "about": null,
            "location": "Mumbai"
        },
        {
            "profile_link": "",
            "name": "Mukhim Deonikar",
            "about": null,
            "location": "Hyderabad"
        },
        {
            "profile_link": "",
            "name": "Pooja Mangtani",
            "about": null,
            "location": "Pune"
        },
        {
            "profile_link": "",
            "name": "Pallabi Baruah",
            "about": null,
            "location": "Bengaluru"
        }
    ],
    "educations_details": "Narsee Monjee Institute of Management Studies",
    "education": [
        {
            "title": "Narsee Monjee Institute of Management Studies",
            "url": "",
            "start_year": "2012",
            "end_year": "2014",
            "description": null,
            "description_html": null,
            "institute_logo_url": null
        },
        {
            "start_year": "2009",
            "end_year": "2012",
            "description": null,
            "description_html": null,
            "institute_logo_url": null
        },
        {
            "start_year": "2005",
            "end_year": "2009",
            "description": null,
            "description_html": null,
            "institute_logo_url": null
        },
        {
            "start_year": "2000",
            "end_year": "2005",
            "description": null,
            "description_html": null,
            "institute_logo_url": null
        }
    ],
    "recommendations_count": null,
    "courses": "[{\"subtitle\":\"-\",\"title\":\"MBA\"}]",
    "languages": null,
    "certifications": [
        {
            "meta": "Issued Jan 2024See credential",
            "subtitle": "LinkedIn",
            "title": "Coach Your Team to Learn, Stretch, and Grow"
        },
        {
            "meta": "Issued Jan 2024See credential",
            "subtitle": "LinkedIn",
            "title": "Key Psychological Principles for Ethical Persuasion"
        },
        {
            "meta": "Issued Jan 2024See credential",
            "subtitle": "LinkedIn",
            "title": "Practical Influencing\u00c2\u00a0Techniques"
        },
        {
            "meta": "Issued Jan 2024See credential",
            "subtitle": "LinkedIn",
            "title": "Psychological Safety: Clear Blocks to Innovation, Collaboration, and Risk-Taking"
        },
        {
            "meta": "Issued May 2023See credential",
            "subtitle": "LinkedIn",
            "title": "How to Speak So People Want to Listen"
        },
        {
            "meta": "Issued Sep 2021See credential",
            "subtitle": "LinkedIn",
            "title": "Confronting Bias: Thriving Across Our Differences"
        },
        {
            "meta": "Issued Sep 2021See credential",
            "subtitle": "LinkedIn",
            "title": "Cultivating a Growth Mindset"
        },
        {
            "meta": "Issued Sep 2021See credential",
            "subtitle": "LinkedIn",
            "title": "Developing a Learning Mindset"
        },
        {
            "meta": "Issued Sep 2021See credential",
            "subtitle": "LinkedIn",
            "title": "How to Make Strategic Thinking a Habit"
        },
        {
            "meta": "Issued Sep 2021See credential",
            "subtitle": "LinkedIn",
            "title": "Managing Innovation"
        },
        {
            "meta": "Issued Aug 2021See credential",
            "subtitle": "LinkedIn",
            "title": "Coaching Employees through Difficult Situations"
        },
        {
            "meta": "Issued Aug 2021See credential",
            "subtitle": "LinkedIn",
            "title": "Delivering Bad News Effectively"
        },
        {
            "meta": "Issued Aug 2021See credential",
            "subtitle": "LinkedIn",
            "title": "Getting Things Done"
        },
        {
            "meta": "Issued Aug 2021See credential",
            "subtitle": "LinkedIn",
            "title": "How to Train Your Brain For Happiness"
        },
        {
            "meta": "Issued Aug 2021See credential",
            "subtitle": "LinkedIn",
            "title": "Learning from Failure"
        },
        {
            "meta": "Issued Aug 2021See credential",
            "subtitle": "LinkedIn",
            "title": "Overcoming Cognitive Bias"
        },
        {
            "meta": "Issued Jan 2021See credential",
            "subtitle": "LinkedIn",
            "title": "Leading with Emotional Intelligence"
        },
        {
            "meta": "Issued Jun 2020Credential ID GOD062020",
            "subtitle": "Go Diverse",
            "title": "Employee Grievance Handling"
        },
        {
            "meta": "Issued Oct 2013See credential",
            "subtitle": "Coursera",
            "title": "New Models of Business in Society"
        },
        {
            "meta": "Issued Sep 2013See credential",
            "subtitle": "Coursera",
            "title": "Social Psychology"
        }
    ],
    "recommendations": null,
    "volunteer_experience": null,
    "followers": 16829.0,
    "connections": 500.0,
    "current_company_company_id": "airbnb",
    "current_company_name": "Airbnb",
    "publications": null,
    "patents": null,
    "projects": null,
    "organizations": null,
    "location": "New Delhi",
    "linkedin_id": "nikhita17",
    "activity": [
        {
            "interaction": "Liked by Nikhita Jain",
            "link": "",
            "title": "Last week was stellar at our global Talent Enablement gathering in the Dublin office! Together, we reflected on our collective accomplishments and\u00e2\u20ac\u00a6",
            "img": null,
            "id": "7271822019946553344"
        },
        {
            "interaction": "Liked by Nikhita Jain",
            "link": "",
            "title": "What an amazing experience it was to attend the event by Indeed ! Thanks for inviting us to the @indeedfutureworks2024bengaluru Impressive insights\u00e2\u20ac\u00a6",
            "img": "",
            "id": "7270844081537245184"
        },
        {
            "interaction": "Liked by Nikhita Jain",
            "link": "",
            "title": "Please don't judge. Or you can judge. I am still proud of what I did. During my MBA at NMIMS, our batch size was around 300. Placements were\u00e2\u20ac\u00a6",
            "img": "",
            "id": "7269194832441405441"
        },
        {
            "interaction": "Liked by Nikhita Jain",
            "link": "",
            "title": "Hiring for seasoned Talent Acquisition leader for a leading Global Client based in Gurgaon. Should have a good blend of 20+ years\u00e2\u20ac\u2122 experience with\u00e2\u20ac\u00a6",
            "img": "",
            "id": "7268313264822910976"
        },
        {
            "interaction": "Liked by Nikhita Jain",
            "link": "",
            "title": "Zomato and Hyperpure by Zomato have an Accounting problem, as well as Accountability problem. After writing multiple emails, sharing data, including\u00e2\u20ac\u00a6",
            "img": "",
            "id": "7267420951972077568"
        }
    ],
    "linkedin_num_id": 107517790.0,
    "honors_and_awards": null,
    "input": {
        "url": ""
    }
}