{
    "city": "Bengaluru, Karnataka, India",
    "position": "|| CSE'20 || Bread Financial || Ex-Cognizant || Analytics || RPA || UiPath | Workato | Power Automate |",
    "experience": [
        {
            "title": "Automation Analyst",
            "location": "Bengaluru, Karnataka, India",
            "description": "• Experienced RPA Analyst, skilled in maintaining, troubleshooting, and enhancing robotic process automation workflows.• Adept at ensuring optimal system performance, collaborating with development teams, and providing user training for seamless automation operations.• Passionate about improving automation efficiency and collaborating with teams for effective solutions.",
            "description_html": "• Experienced RPA Analyst, skilled in maintaining, troubleshooting, and enhancing robotic process automation workflows.• Adept at ensuring optimal system performance, collaborating with development teams, and providing user training for seamless automation operations.• Passionate about improving automation efficiency and collaborating with teams for effective solutions. <!---->",
            "duration": "Jun 2024 - Present 7 months",
            "start_date": "Jun 2024",
            "end_date": "Present",
            "duration_short": "7 months",
            "company": "Bread Financial",
            "company_id": "bread-financial",
            "url": "",
            "company_logo_url": ""
        },
        {
            "title": "Cognizant",
            "location": "Bengaluru, Karnataka, India",
            "description_html": null,
            "duration": "3 years",
            "positions": [
                {
                    "subtitle": "Cognizant",
                    "meta": "Jun 2022 - May 2024 2 years",
                    "description": "• Seasoned RPA Production Engineer with experience serving US-based Banking & Financial clients, and Robotics Subject Matter Expert for a Health Care client.• Proficient in utilizing Automation Tools such as UiPath and UiPath Orchestrator, and along with skills in Tableau, WinSQL, Power Automate, and SharePoint.• Proven expertise in designing Data Dashboards to enhance insights and facilitate better understanding.",
                    "duration": "Jun 2022 May 2024 2 years",
                    "start_date": "Jun 2022",
                    "end_date": "May 2024",
                    "duration_short": "2 years",
                    "title": "Programmer Analyst (Robotic Process Automation)",
                    "description_html": "• Seasoned RPA Production Engineer with experience serving US-based Banking &amp; Financial clients, and Robotics Subject Matter Expert for a Health Care client.<br>• Proficient in utilizing Automation Tools such as UiPath and UiPath Orchestrator, and along with skills in Tableau, WinSQL, Power Automate, and SharePoint.<br>• Proven expertise in designing Data Dashboards to enhance insights and facilitate better understanding. <!---->"
                },
                {
                    "subtitle": "Cognizant",
                    "meta": "Jun 2021 - May 2022 1 year",
                    "duration": "Jun 2021 May 2022 1 year",
                    "start_date": "Jun 2021",
                    "end_date": "May 2022",
                    "duration_short": "1 year",
                    "title": "Programmer Analyst Trainee (RPA)",
                    "description_html": null
                }
            ],
            "company": "Cognizant",
            "company_id": "cognizant",
            "url": "",
            "company_logo_url": null
        },
        {
            "title": "Campus Ambassador",
            "location": "Guwahati, Assam, India",
            "description_html": null,
            "duration": "Dec 2020 Mar 2021 4 months",
            "start_date": "Dec 2020",
            "end_date": "Mar 2021",
            "duration_short": "4 months",
            "company": "Udgam (The Annual Entrepreneurship Summit of IIT Guwahati)",
            "company_id": "udgam-the-annual-entrepreneurship-summit-of-iit-guwahati",
            "url": "",
            "company_logo_url": ""
        },
        {
            "title": "Software Engineering Virtual Internship",
            "description_html": null,
            "duration": "Dec 2020 Jan 2021 2 months",
            "start_date": "Dec 2020",
            "end_date": "Jan 2021",
            "duration_short": "2 months",
            "company": "JPMorgan Chase & Co.",
            "company_id": "jpmorganchase",
            "url": "",
            "company_logo_url": ""
        },
        {
            "title": "Summer Intern",
            "location": "Varanasi Area, India",
            "description": "Organization- Technical Training Center, DLW, VaranasiProject Name- IOT based Smart System using Heat Sensor.",
            "description_html": "Organization- Technical Training Center, DLW, VaranasiProject Name- IOT based Smart System using Heat Sensor. <!---->",
            "duration": "Jun 2019 Jul 2019 2 months",
            "start_date": "Jun 2019",
            "end_date": "Jul 2019",
            "duration_short": "2 months",
            "company": "Indian Railways",
            "company_id": "indian-railways-new",
            "url": "",
            "company_logo_url": ""
        }
    ],
    "education": [
        {
            "title": "SkilloVilla",
            "degree": "Certificate",
            "field": "Data Analytics",
            "url": "",
            "start_year": "2023",
            "end_year": "2023",
            "description": "• Proficient in gathering, interpreting, and visualizing data to extract insights. • Skilled in using various tools and techniques to make data-driven decisions, optimize processes, and drive business growth. • Strong analytical, problem-solving, and communication skills to convey complex findings to stakeholders. • Covered various tools, methodologies, and techniques, including data visualization, statistical analysis, and machine learning. • Provided hands-on experience with… Show more",
            "description_html": "• Proficient in gathering, interpreting, and visualizing data to extract insights.• Skilled in using various tools and techniques to make data-driven decisions, optimize processes, and drive business growth.• Strong analytical, problem-solving, and communication skills to convey complex findings to stakeholders.• Covered various tools, methodologies, and techniques, including data visualization, statistical analysis, and machine learning.• Provided hands-on experience with…",
            "institute_logo_url": ""
        },
        {
            "title": "Dr. A.P.J. Abdul Kalam Technical University",
            "degree": "Bachelor of Technology - BTech",
            "field": "Computer Science and Engineering",
            "url": "",
            "start_year": "2016",
            "end_year": "2020",
            "description": null,
            "description_html": null,
            "institute_logo_url": ""
        },
        {
            "title": "Indian Institute of Remote Sensing (IIRS), Indian Space Research Organization (ISRO)",
            "degree": "Certification",
            "field": "Geocomputation and Geoweb Services",
            "url": "",
            "description": null,
            "description_html": null,
            "institute_logo_url": ""
        }
    ],
    "courses": null,
    "certifications": [
        {
            "meta": "Issued Dec 2024Credential ID 0241200012See credential",
            "subtitle": "GLSS (GoLeanSixSigma.com)",
            "title": "Lean Six Sigma Yellow Belt"
        },
        {
            "meta": "Issued Apr 2024Credential ID B33CC406516F4001See credential",
            "subtitle": "Microsoft",
            "title": "Microsoft Certified: Azure Fundamentals"
        },
        {
            "meta": "Issued Dec 2023",
            "subtitle": "SkilloVilla",
            "title": "Data Analyst"
        },
        {
            "meta": "Issued Aug 2023Credential ID Certificate_08112023105046752",
            "subtitle": "UiPath",
            "title": "Automation Business Analysis Fundamentals"
        },
        {
            "meta": "Issued Aug 2023Credential ID d99a59280599See credential",
            "subtitle": "HackerRank",
            "title": "SQL- Basic & Intermediate"
        },
        {
            "meta": "Issued Apr 2022Credential ID A09C25A74122BF81See credential",
            "subtitle": "Microsoft",
            "title": "Microsoft Certified: Power Platform Fundamentals"
        },
        {
            "meta": "Issued Dec 2021Credential ID rve469mhvfanSee credential",
            "subtitle": "Workato",
            "title": "Automation Pro I Certification"
        },
        {
            "meta": "Issued Dec 2021Credential ID cgybb6iv9fjnSee credential",
            "subtitle": "Workato",
            "title": "Automation Pro II Certification"
        },
        {
            "meta": "Issued Nov 2021",
            "subtitle": "Udemy",
            "title": "RPA - Process Automation using UiPath - Beginner to Expert"
        },
        {
            "meta": "Issued Jun 2021",
            "subtitle": "UiPath",
            "title": "RPA Developer Foundation & Advanced"
        },
        {
            "meta": "Issued Jan 2021See credential",
            "subtitle": "Udemy",
            "title": "Build Responsive Websites using HTML, CSS, JavaScript and Bootstrap"
        },
        {
            "meta": "Issued Jun 2020",
            "subtitle": "Tata Consultancy Services",
            "title": "Introduction to Artificial Intelligence"
        },
        {
            "meta": "Issued Apr 2020",
            "subtitle": "Skillzcafe",
            "title": "Fundamentals Data Analysis and Decision Making Models"
        },
        {
            "meta": "Issued Apr 2019",
            "subtitle": "PRASTUTI",
            "title": "Artificial Intelligence Workshop"
        }
    ],
    "current_company_name": "Bread Financial",
    "publications": null,
    "patents": null,
    "projects": "[{\"title\":\"IOT based Smart System using Heat Sensor\"}]",
    "honors_and_awards": [
        {
            "title": "Cognizant Cheer Award",
            "publication": "Cognizant",
            "date": "2023-02-01T00:00:00.000Z",
            "description": "Received an Award for Working as One in 2021 & 2022"
        },
        {
            "title": "Cognizant Cheer Award",
            "publication": "Cognizant",
            "date": "2021-10-01T00:00:00.000Z",
            "description": "Received an Award for providing immense support towards Cognizant® as a Batch Owner."
        }
    ]
}