{
    "id": "varundeshpande14",
    "name": "Varun Deshpande",
    "city": "Bengaluru, Karnataka, India",
    "country_code": "IN",
    "position": null,
    "about": null,
    "posts": null,
    "groups": null,
    "current_company": {
        "link": "",
        "name": "Juno",
        "company_id": "junofinancehq"
    },
    "experience": null,
    "people_also_viewed": [
        {
            "profile_link": "",
            "name": "Marat Tsirelson",
            "about": null,
            "location": "Greater Philadelphia"
        },
        {
            "profile_link": "",
            "name": "Brant Bukowsky",
            "about": null,
            "location": "United States"
        },
        {
            "profile_link": "",
            "name": "Can Kisagun",
            "about": null,
            "location": "San Francisco, CA"
        },
        {
            "profile_link": "",
            "name": "Cara Conde",
            "about": "FC Tucker Company, Inc",
            "location": "San Francisco, CA"
        },
        {
            "profile_link": "",
            "name": "Ratnesh Ray",
            "about": null,
            "location": "Bengaluru"
        },
        {
            "profile_link": "",
            "name": "Philip Cortes",
            "about": null,
            "location": "Alamo, CA"
        },
        {
            "profile_link": "",
            "name": "Sveinn Valfells",
            "about": null,
            "location": "Iceland"
        },
        {
            "profile_link": "",
            "name": "Raj Gilda",
            "about": null,
            "location": "Pune"
        },
        {
            "profile_link": "",
            "name": "Tony Gallippi",
            "about": null,
            "location": "Alpharetta, GA"
        },
        {
            "profile_link": "",
            "name": "Lucas Moraes",
            "about": null,
            "location": "San Francisco Bay Area"
        }
    ],
    "educations_details": "Birla Institute of Technology and Science, Pilani",
    "education": [
        {
            "title": "Birla Institute of Technology and Science, Pilani",
            "url": "",
            "start_year": "2008",
            "end_year": "2012",
            "description": null,
            "description_html": null,
            "institute_logo_url": null
        }
    ],
    "recommendations_count": null,
    "courses": null,
    "languages": [
        {
            "subtitle": " Full professional proficiency ",
            "title": " English "
        },
        {
            "subtitle": " Full professional proficiency ",
            "title": " Hindi "
        },
        {
            "subtitle": " Native or bilingual proficiency ",
            "title": " Marathi "
        }
    ],
    "certifications": null,
    "recommendations": null,
    "volunteer_experience": null,
    "followers": 31859.0,
    "connections": 500.0,
    "current_company_company_id": "junofinancehq",
    "current_company_name": "Juno",
    "publications": null,
    "patents": null,
    "projects": null,
    "organizations": null,
    "location": "Bengaluru",
    "linkedin_id": "varundeshpande14",
    "activity": [
        {
            "interaction": "Liked by Varun Deshpande",
            "link": "",
            "title": "I shipped an app to the Apple Store\u00e2\u20ac\u00a6",
            "img": "",
            "id": "7275585836635594753"
        },
        {
            "interaction": "Liked by Varun Deshpande",
            "link": "",
            "title": "Excited to share that ParaFi Capital\u00e2\u20ac\u00a6",
            "img": "",
            "id": "250"
        },
        {
            "interaction": "Liked by Varun Deshpande",
            "link": "",
            "title": "Bleap, a mobile-first neobank founded\u00e2\u20ac\u00a6",
            "img": "",
            "id": "7272270849091461120"
        },
        {
            "interaction": "Liked by Varun Deshpande",
            "link": "",
            "title": "Every 'processing' screen in payments\u00e2\u20ac\u00a6",
            "img": "",
            "id": "7276234109893451776"
        },
        {
            "interaction": "Liked by Varun Deshpande",
            "link": "",
            "title": "MoneyLion is closing out the year on a\u00e2\u20ac\u00a6",
            "img": "",
            "id": "7275900369312870400"
        },
        {
            "interaction": "Liked by Varun Deshpande",
            "link": "",
            "title": "Posted my take on \"Debanking\" on my\u00e2\u20ac\u00a6",
            "img": "",
            "id": "7275900559042207744"
        },
        {
            "interaction": "Liked by Varun Deshpande",
            "link": "",
            "title": "Unsurprisingly, got lots of questions\u00e2\u20ac\u00a6",
            "img": "",
            "id": "7275460975388958720"
        },
        {
            "interaction": "Liked by Varun Deshpande",
            "link": "",
            "title": "Been building AI agents for Salesforce\u00e2\u20ac\u00a6",
            "img": "",
            "id": "7275747775437328386"
        },
        {
            "interaction": "Liked by Varun Deshpande",
            "link": "",
            "title": "2024 was a landmark year for crypto\u00e2\u20ac\u00a6",
            "img": "",
            "id": "7275673793384095745"
        },
        {
            "interaction": "Liked by Varun Deshpande",
            "link": "",
            "title": "Another incredible year at Zero Hash!\u00e2\u20ac\u00a6",
            "img": "",
            "id": "7275510558458601472"
        },
        {
            "interaction": "Liked by Varun Deshpande",
            "link": "",
            "title": "Teams are being told to wait until Jan\u00e2\u20ac\u00a6",
            "img": "",
            "id": "7275300509370990592"
        },
        {
            "interaction": "Liked by Varun Deshpande",
            "link": "",
            "title": "Proud Moment for ftcash! Thrilled to\u00e2\u20ac\u00a6",
            "img": "",
            "id": "7275389077342818305"
        },
        {
            "interaction": "Liked by Varun Deshpande",
            "link": "",
            "title": "I\u00e2\u20ac\u2122m proud to announce Parafin\u00e2\u20ac\u2122s $100M\u00e2\u20ac\u00a6",
            "img": "",
            "id": "7274826172629147649"
        },
        {
            "interaction": "Liked by Varun Deshpande",
            "link": "",
            "title": "Glimpses from last week\u00e2\u20ac\u2122s USC Viterbi\u00e2\u20ac\u00a6",
            "img": "",
            "id": "7274790262952902656"
        },
        {
            "interaction": "Liked by Varun Deshpande",
            "link": "",
            "title": "Ep. 13 of Tokenized Podcast: The\u00e2\u20ac\u00a6",
            "img": "",
            "id": "13"
        },
        {
            "interaction": "Liked by Varun Deshpande",
            "link": "",
            "title": "In the Australian Financial Review\u00e2\u20ac\u00a6",
            "img": "",
            "id": "7272743944067686401"
        },
        {
            "interaction": "Liked by Varun Deshpande",
            "link": "",
            "title": "We are excited to announce that the New\u00e2\u20ac\u00a6",
            "img": "",
            "id": "7274423226489839617"
        },
        {
            "interaction": "Liked by Varun Deshpande",
            "link": "",
            "title": "Announcing our Series B \u00f0\u0178\u0161\u20ac \u00f0\u0178\u2122\u0152 We\u00e2\u20ac\u2122ve\u00e2\u20ac\u00a6",
            "img": "",
            "id": "7274809246406365184"
        }
    ],
    "linkedin_num_id": 53031022.0,
    "honors_and_awards": null,
    "input": {
        "url": ""
    }
}