{
    "id": "anthonypierri",
    "name": "Anthony Pierri 🎸",
    "city": "Chicago, Illinois, United States",
    "country_code": "US",
    "position": null,
    "posts": null,
    "groups": null,
    "current_company": {
        "link": "",
        "name": "FletchPMM",
        "company_id": "fletch-pmm"
    },
    "experience": null,
    "people_also_viewed": [
        {
            "profile_link": "",
            "name": "Timothy Tyler, DMin.",
            "about": "Pastor of Shorter Community AME Church, Denver",
            "location": "Denver Metropolitan Area"
        },
        {
            "profile_link": "",
            "name": "Phillip Brande",
            "about": "Pastor at Farmington Baptist Church",
            "location": "Mocksville, NC"
        },
        {
            "profile_link": "",
            "name": "Garrett Kell",
            "about": "Pastor at Del Ray Baptist Church",
            "location": "New Alexandria, VA"
        },
        {
            "profile_link": "",
            "name": "Ron L Buford",
            "about": "Writer, Speaker, Pastor, Consultant, Seminarian",
            "location": "San Francisco Bay Area"
        },
        {
            "profile_link": "",
            "name": "Mitch Green",
            "about": "Teaching Pastor @ Ascend Bible Church",
            "location": "Greater Indianapolis"
        },
        {
            "profile_link": "",
            "name": "Wes Flaugh",
            "about": "Pastor at Calvary Baptist Church",
            "location": "Colcord, OK"
        },
        {
            "profile_link": "",
            "name": "Josh Morris",
            "about": "who knows",
            "location": "Roanoke, TX"
        },
        {
            "profile_link": "",
            "name": "Jeff Whye",
            "about": "Campus Pastor at Sandals Church",
            "location": "Riverside, CA"
        },
        {
            "profile_link": "",
            "name": "Brian Kinsey",
            "about": "Pastor at First Pentecostal Church",
            "location": "Pensacola, FL"
        },
        {
            "profile_link": "",
            "name": "Howie Snyder",
            "about": "Administrative Pastor at River Church",
            "location": "Denver, CO"
        }
    ],
    "educations_details": "Denver Seminary",
    "education": [
        {
            "title": "Denver Seminary",
            "url": "",
            "start_year": "2018",
            "end_year": "2021",
            "description": null,
            "description_html": null,
            "institute_logo_url": null
        },
        {
            "start_year": "2013",
            "end_year": "2015",
            "description": null,
            "description_html": null,
            "institute_logo_url": null
        },
        {
            "start_year": "2011",
            "end_year": "2013",
            "description": null,
            "description_html": null,
            "institute_logo_url": null
        }
    ],
    "recommendations_count": null,
    "courses": null,
    "languages": null,
    "certifications": null,
    "recommendations": null,
    "volunteer_experience": null,
    "followers": 62099.0,
    "connections": 500.0,
    "current_company_company_id": "fletch-pmm",
    "current_company_name": "FletchPMM",
    "publications": null,
    "patents": null,
    "projects": null,
    "organizations": null,
    "location": "Chicago",
    "linkedin_id": "anthonypierri",
    "activity": [
        {
            "interaction": "Liked by Anthony Pierri 🎸",
            "link": "",
            "title": "Listen up: Writing for the…",
            "img": "",
            "id": "7278317771774480385"
        }
    ],
    "linkedin_num_id": 385358969.0,
    "honors_and_awards": null,
    "input": {
        "url": ""
    }
}