{
    "id": "nathan-downey-8472a6226",
    "name": "Nathan Downey",
    "city": "London, England, United Kingdom",
    "country_code": "GB",
    "position": null,
    "posts": null,
    "groups": null,
    "current_company": {
        "link": "",
        "name": "Vanquish Solutions",
        "company_id": "vanquish-solutions"
    },
    "experience": null,
    "people_also_viewed": null,
    "educations_details": null,
    "education": null,
    "recommendations_count": null,
    "courses": null,
    "languages": null,
    "certifications": null,
    "recommendations": null,
    "volunteer_experience": null,
    "followers": 3908.0,
    "connections": 500.0,
    "current_company_company_id": "vanquish-solutions",
    "current_company_name": "Vanquish Solutions",
    "publications": null,
    "patents": null,
    "projects": null,
    "organizations": null,
    "location": "London",
    "linkedin_id": "nathan-downey-8472a6226",
    "activity": [
        {
            "interaction": "Shared by Nathan Downey",
            "link": "",
            "title": "Looking forward to attending Finance…",
            "img": "",
            "id": "7260599099408662529"
        },
        {
            "interaction": "Liked by Nathan Downey",
            "link": "",
            "title": "The pound is on track for its fourth…",
            "img": "",
            "id": "7229457177541836801"
        },
        {
            "interaction": "Liked by Nathan Downey",
            "link": "",
            "title": "UK house prices rose by 0.8% in July…",
            "img": "",
            "id": "7227290869882597377"
        },
        {
            "interaction": "Liked by Nathan Downey",
            "link": "",
            "title": "Global markets tumbled on Monday…",
            "img": "",
            "id": "7226934620028620801"
        },
        {
            "interaction": "Liked by Nathan Downey",
            "link": "",
            "title": "Having an office in the heart of Canary…",
            "img": "",
            "id": "7221140908556070912"
        },
        {
            "interaction": "Shared by Nathan Downey",
            "link": "",
            "title": "Last Friday, we had one of our partners…",
            "img": "",
            "id": "7218573710960533504"
        },
        {
            "interaction": "Shared by Nathan Downey",
            "link": "",
            "title": "Great meeting at Hampton Tower, Canary…",
            "img": "",
            "id": "7209150579133005824"
        },
        {
            "interaction": "Shared by Nathan Downey",
            "link": "",
            "title": "✨ A Memorable Evening at The Grove's…",
            "img": "",
            "id": "7207350831594008576"
        },
        {
            "interaction": "Liked by Nathan Downey",
            "link": "",
            "title": "Busy start to the year! Markets are…",
            "img": "",
            "id": "7161394754470002689"
        },
        {
            "interaction": "Shared by Nathan Downey",
            "link": "",
            "title": "Hello LinkedIn Community, Exciting…",
            "img": "",
            "id": "7161317563967127552"
        }
    ],
    "linkedin_num_id": 950259511.0,
    "honors_and_awards": null,
    "input": {
        "url": ""
    }
}